fastpypi/__init__.py
fastpypi/credentials.py
fastpypi/fastpypi_core.py
fastpypi/setup.py
fastpypi-1.0.0.dist-info/LICENSE
fastpypi-1.0.0.dist-info/METADATA
fastpypi-1.0.0.dist-info/WHEEL
fastpypi-1.0.0.dist-info/top_level.txt
fastpypi-1.0.0.dist-info/RECORD
