Metadata-Version: 2.1
Name: fastpypi
Version: 1.0.0
Summary: A package enabling user to create and update existing PyPI packages in an easy-to-use gui.
Home-page: https://github.com/DovaX/fastpypi
Author: DovaX
Author-email: dovax.ai@gmail.com
Classifier: Programming Language :: Python :: 3
Classifier: License :: OSI Approved :: MIT License
Classifier: Operating System :: OS Independent
Requires-Python: >=3.6
License-File: LICENSE
Requires-Dist: dogui
Requires-Dist: keepvariable
